{
  "audio_file": "D:\\Productions\\meetingminutes\\data\\학과회의.m4a",
  "model": "large-v3-turbo",
  "transcribe_time_seconds": 114.30500674247742,
  "segment_count": 114,
  "total_text_length": 5422,
  "segments": [
    {
      "start": 28.82,
      "end": 31.584,
      "text": "성원 보고 부탁드리겠습니다.",
      "speaker": null,
      "confidence": 0.428
    },
    {
      "start": 46.984,
      "end": 47.424,
      "text": "안녕하십니까.",
      "speaker": null,
      "confidence": 0.702
    },
    {
      "start": 48.165,
      "end": 54.974,
      "text": "26년도 맞이하여 저희가 1차 수의과 대학 학과 회의를 시작하도록 하겠습니다.",
      "speaker": null,
      "confidence": 0.42069999999999996
    },
    {
      "start": 54.994,
      "end": 56.937,
      "text": "오늘 좀",
      "speaker": null,
      "confidence": 0.4835
    },
    {
      "start": 57.524,
      "end": 69.962,
      "text": "논의하셔야 될 부분이 제법 많이 있는데 논의에 앞서서 저희가 앞으로 어떻게 학과회의를 진행할 것인가에 대해서 많이 논의를 했었는데요.",
      "speaker": null,
      "confidence": 0.6511111111111112
    },
    {
      "start": 69.982,
      "end": 79.836,
      "text": "우선적으로는 학과회의는 그 전에는 학장님이 주제를 주로 하고 그러셨는데 아무래도 교수님들도 많아지시기도 했고",
      "speaker": null,
      "confidence": 0.6278461538461539
    },
    {
      "start": 79.816,
      "end": 88.568,
      "text": "그 다음에 학과회의는 학과장님께서 주재하는 게 저는 맞다라고 생각하고 저희가 의견을 통일을 했습니다.",
      "speaker": null,
      "confidence": 0.5214615384615384
    },
    {
      "start": 88.969,
      "end": 96.179,
      "text": "그래서 특별한 사항 이외에는 학과회의는 우리 강찬근 부학장님께서 주재를 하시는 걸로 하도록 하겠습니다.",
      "speaker": null,
      "confidence": 0.5925384615384615
    },
    {
      "start": 96.199,
      "end": 99.243,
      "text": "이 점 양해 부탁드리겠습니다.",
      "speaker": null,
      "confidence": 0.6672499999999999
    },
    {
      "start": 99.263,
      "end": 103.309,
      "text": "첫 번째로 제가 긴급 현안 주제인데요.",
      "speaker": null,
      "confidence": 0.7028333333333334
    },
    {
      "start": 104.2,
      "end": 113.175,
      "text": "신구대조문표라고 학사관리규정을 나눠드린게 있습니다.",
      "speaker": null,
      "confidence": 0.542
    },
    {
      "start": 113.195,
      "end": 119.205,
      "text": "이게 다음주 학무회의에서 논의가 될 사항인데",
      "speaker": null,
      "confidence": 0.7385
    },
    {
      "start": 120.62,
      "end": 125.867,
      "text": "내용을 보게 되면 37조의 이 항목을 다 삭제를 하는 내용입니다.",
      "speaker": null,
      "confidence": 0.7175
    },
    {
      "start": 125.887,
      "end": 139.886,
      "text": "그 이유는 만들어진 배경이 우리 학교가 중도 입퇴할율이라든가 학생수가 제적당하고 그만두는 경우가 많아서 대학교 평가에서 아주 낮은 점수를 받고 있답니다.",
      "speaker": null,
      "confidence": 0.6437499999999999
    },
    {
      "start": 139.906,
      "end": 142.83,
      "text": "그래서 이 TF팀 교무처하고에서",
      "speaker": null,
      "confidence": 0.5235
    },
    {
      "start": 143.637,
      "end": 162.625,
      "text": "그거를 타계 확인 방법 중에 하나가 37조의 2인 재입학 제한 내용을 없애자 그게 이제 결정이 났고요 그 다음에 각 학과별로 이거를 의견 조회를 했었습니다만 저희 쪽에서도 이런 자세한 내용을",
      "speaker": null,
      "confidence": 0.6651034482758621
    },
    {
      "start": 162.605,
      "end": 166.529,
      "text": "확인하지 않고 미스를 한 거죠.",
      "speaker": null,
      "confidence": 0.6629999999999999
    },
    {
      "start": 166.549,
      "end": 170.674,
      "text": "미스를 해서 의견 없음으로 가게 됐습니다.",
      "speaker": null,
      "confidence": 0.5201666666666666
    },
    {
      "start": 170.694,
      "end": 181.466,
      "text": "그래서 의견 없음으로 가게 돼서 본부 측에서는 37조의 이의사항을 다 삭제하는 걸로 계정안을 보게 되면 다 삭제된 걸로 이렇게 나오게 됐습니다.",
      "speaker": null,
      "confidence": 0.44652380952380955
    },
    {
      "start": 181.486,
      "end": 187.853,
      "text": "그런데 아직도 절차는 조금 남아 있습니다만 그래서 문제점을 좀 제가 말씀을 드리면은",
      "speaker": null,
      "confidence": 0.7924166666666665
    },
    {
      "start": 188.322,
      "end": 193.23,
      "text": "37조의 현행에 있어서 1항 생략되어 있고요.",
      "speaker": null,
      "confidence": 0.7775000000000002
    },
    {
      "start": 193.25,
      "end": 213.925,
      "text": "2항 재학연한을 초과하여 제적된 사람으로서 1년이 경과되지 않은 사람 3번 학사 징계 및 예과에서 유급으로 제적된 사람으로서 1년이 경과되지 않은 사람 4번 수의학과 및 의학과에서 징계 유급",
      "speaker": null,
      "confidence": 0.8608888888888891
    },
    {
      "start": 213.905,
      "end": 223.712,
      "text": "재학 연안 초과로 제적된 사람 이 항목을 다 삭제를 하는 걸로 지금 법제심의위원회, 학무회를 통과해서 법제심의위원회를 갈 건데",
      "speaker": null,
      "confidence": 0.7517777777777777
    },
    {
      "start": 224.688,
      "end": 229.076,
      "text": "여기서 문제가 되는 게 뭐냐면 1번은 생략됐고요.",
      "speaker": null,
      "confidence": 0.8412857142857143
    },
    {
      "start": 229.397,
      "end": 231.581,
      "text": "2번, 3번은 큰 문제는 없습니다.",
      "speaker": null,
      "confidence": 0.7555999999999999
    },
    {
      "start": 231.601,
      "end": 242.781,
      "text": "저희도 충분히 공감하는 부분인데 4번의 사항에 수의학과 및 의학과에서 징계 항목이 문제가 됩니다.",
      "speaker": null,
      "confidence": 0.6558461538461539
    },
    {
      "start": 243.302,
      "end": 244.705,
      "text": "즉 학생들이",
      "speaker": null,
      "confidence": 0.475
    },
    {
      "start": 244.685,
      "end": 261.124,
      "text": "혹시라도 우리과에서도 그런 일이 있었는데 범죄 행위에 연루된다거나 아니면 학생으로서 품행에 문제가 돼서 징계돼서 제적된 학생들 같은 경우에는 이 항목이 없어지게 되면",
      "speaker": null,
      "confidence": 0.7531363636363637
    },
    {
      "start": 263.989,
      "end": 276.43,
      "text": "그런 문제점이 있어서 지금 현재 약대하고 여기에 관련된 건 의과대학, 수의과대학 이런 부분이 좀 많이 문제가 되는데 지금 학장님들하고는 저희가 논의를 했고요.",
      "speaker": null,
      "confidence": 0.7853181818181819
    },
    {
      "start": 276.41,
      "end": 286.267,
      "text": "다음 주 화요일에 있는 학무회의에서 이 부분에서 징계 부분은 살려두자.",
      "speaker": null,
      "confidence": 0.784
    },
    {
      "start": 286.287,
      "end": 300.612,
      "text": "그래서 수의학과 및 의학과에서 징계로 제적된 사람은 재입학을 제한한다는 내용을 살려두려고 의견은 통일됐습니다만 이 부분도 교수님들께서 의견을 주시면",
      "speaker": null,
      "confidence": 0.6527777777777778
    },
    {
      "start": 300.592,
      "end": 308.644,
      "text": "이 부분도 같이 논의를 해서 이 부분은 꼭 저희가 관철을 시켜야 될 것 같은데 의견이 어떠신지.",
      "speaker": null,
      "confidence": 0.696625
    },
    {
      "start": 309.198,
      "end": 323.494,
      "text": "지금 학생 하나 얘기를 하면 예과에서 그 학생 한 명이 불미스러운 인류에서 제적이 된 상태인데 그 친구 같은 경우는 지금 항소를 계속하고 있는 거예요.",
      "speaker": null,
      "confidence": 0.6220833333333334
    },
    {
      "start": 329.481,
      "end": 331.543,
      "text": "계속 지금 항소를 하고 있는 상황이고 그래서",
      "speaker": null,
      "confidence": 0.48928571428571427
    },
    {
      "start": 332.3,
      "end": 338.087,
      "text": "이게 만약에 없어지게 되면 그 학생을 바로 내년에 복학을 하게 됩니다.",
      "speaker": null,
      "confidence": 0.5388181818181819
    },
    {
      "start": 338.107,
      "end": 348.539,
      "text": "그 다음에 또 본과 4학년에서도 좀 문제가 됐던 학생이 하나 있어서 제적이 됐는데 그 학생 또한 이게 풀어지게 되면 재입학이 가능하게 됩니다.",
      "speaker": null,
      "confidence": 0.40390909090909105
    },
    {
      "start": 348.559,
      "end": 355.827,
      "text": "그러게 되면 학생들 피해를 받았던 학생들이라든가 그런 친구들한테도 영향을 미칠 수가 있어서",
      "speaker": null,
      "confidence": 0.6495833333333333
    },
    {
      "start": 369.248,
      "end": 371.693,
      "text": "우리가 못 받을 이유가 없는 겁니다.",
      "speaker": null,
      "confidence": 0.4558333333333333
    },
    {
      "start": 371.713,
      "end": 372.735,
      "text": "이 항목이 없기 때문에.",
      "speaker": null,
      "confidence": 0.48324999999999996
    },
    {
      "start": 430.007,
      "end": 436.417,
      "text": "맞습니다.",
      "speaker": null,
      "confidence": 0.917
    },
    {
      "start": 485.684,
      "end": 498.066,
      "text": "경상국립대학교 학칙 2절을 보게 되면 징계 사유를 보게 되면 재입학 제한에서 37조에 이어",
      "speaker": null,
      "confidence": 0.724076923076923
    },
    {
      "start": 499.092,
      "end": 501.477,
      "text": "다음 각호에 해당하는 사람은 재입학을 불허합니다.",
      "speaker": null,
      "confidence": 0.693
    },
    {
      "start": 501.497,
      "end": 502.278,
      "text": "1.",
      "speaker": null,
      "confidence": 0.992
    },
    {
      "start": 502.639,
      "end": 508.971,
      "text": "학책 따라 제적된 후 3년이 경과되지 않은 사람 재입학 불허고요.",
      "speaker": null,
      "confidence": 0.8173
    },
    {
      "start": 509.592,
      "end": 519.531,
      "text": "재학연한을 초과하여 제적된 사람으로 1년이 경과되지 않은 사람 이건 이제 살려지게 되고 세 번째 학사 징계 및",
      "speaker": null,
      "confidence": 0.8201176470588235
    },
    {
      "start": 520.034,
      "end": 539.916,
      "text": "예과에서 유급으로 제작된 사람으로 1년이 경과되지 않은 사람 네 번째 수의학과 및 의학과에서 징계 유급 제약 연안 초과로 제작된 사람 이게 학사관리 규정에서 나와 있는 내용인데 네 번째가 수의학과 및 의학과에서",
      "speaker": null,
      "confidence": 0.878032258064516
    },
    {
      "start": 539.896,
      "end": 550.75,
      "text": "징계유국제학연합총으로 제작된 사람에서 이 징계 부분이 여기에 들어가 있어서 이 부분은 여기에 없어지게 되는 겁니다 빨간색으로 되어 있는 내용이",
      "speaker": null,
      "confidence": 0.6744210526315789
    },
    {
      "start": 640.858,
      "end": 650.155,
      "text": "회장님이 잠깐 설명을 해주실 겁니다.",
      "speaker": null,
      "confidence": 0.6148
    },
    {
      "start": 650.596,
      "end": 657.99,
      "text": "학사지원가에서 학사관리규정 제37조의 이 재입학의 제안이라는 부분에서",
      "speaker": null,
      "confidence": 0.5048571428571428
    },
    {
      "start": 739.983,
      "end": 766.378,
      "text": "그래서 학사지원과에서는 이 이야기를 하니까 어차피 재입 파악을 하려고 할 때",
      "speaker": null,
      "confidence": 0.44299999999999995
    },
    {
      "start": 766.358,
      "end": 781.38,
      "text": "단대에서 재입학 신사위원회가 있는데 거기서 조정하면 되지 않느냐 하는데 제가 몇 년 있어보니까 한 사람이 계속 재입학 신청을 하는 것 같더라고요.",
      "speaker": null,
      "confidence": 0.5672857142857143
    },
    {
      "start": 781.36,
      "end": 785.965,
      "text": "그렇게 되면 학사지원과에 민원도 있었거든요.",
      "speaker": null,
      "confidence": 0.40779999999999994
    },
    {
      "start": 785.985,
      "end": 789.209,
      "text": "왜 내가 떨어졌느냐고.",
      "speaker": null,
      "confidence": 0.49
    },
    {
      "start": 833.352,
      "end": 856.542,
      "text": "그런데 이제 만약에 우리가 4호는 삭제가 되고 저희처럼 징계를 받아서 제적이 된 친구는 어찌되었건 이 1호에",
      "speaker": null,
      "confidence": 0.47481250000000014
    },
    {
      "start": 953.907,
      "end": 975.797,
      "text": "지금 교수님들 말씀 중에 한 부분은 우리는 이제 다른 과들 유급제도가 있어 가지고 공부 못한 애들은 당연히 이제 더 공부하게끔 하고 그러는데 요게 다 없어지게 되면은 제적이라는 게 유급 그런 게 의미가 없어질 것 같아요 학점을 줘도 얘가 유급할 때 다시 다니면 되니까",
      "speaker": null,
      "confidence": 0.7671162790697674
    },
    {
      "start": 1013.14,
      "end": 1029.477,
      "text": "유급, 제약이나 저거.",
      "speaker": null,
      "confidence": 0.428
    },
    {
      "start": 1062.346,
      "end": 1080.304,
      "text": "다른 교수님 의견도 37조의 2에 있는 항 2항 3항 4항 이거는 다 살리자 지금 빨갛게 해놓으면 다 살려놔야 된다고",
      "speaker": null,
      "confidence": 0.5373684210526315
    },
    {
      "start": 1084.231,
      "end": 1097.599,
      "text": "관련된 거는 예과 관련된 거고 징계 관련된 거는 우리 대학하고 약대하고 수의대가 거의 다 되고 다른 대학교는 관심도 없습니다.",
      "speaker": null,
      "confidence": 0.7478947368421053
    },
    {
      "start": 1098.02,
      "end": 1118.458,
      "text": "그러면 제가 교수님들 의견에 따라서 오늘 다시 약대 교수님하고 이대 교수님 학장님들하고 같이 만나서 이 세 가지는 우리는 살려두는 게 삭제하지 않고 그대로 유지하는 걸로 그렇게 의견을 제가 구하도록 하겠습니다.",
      "speaker": null,
      "confidence": 0.5582333333333335
    },
    {
      "start": 1120.6,
      "end": 1127.667,
      "text": "지금부터 학과의 주제 구학장님께서 진행 부탁드리겠습니다.",
      "speaker": null,
      "confidence": 0.5381666666666667
    },
    {
      "start": 1128.007,
      "end": 1144.324,
      "text": "첫 번째 안건입니다.",
      "speaker": null,
      "confidence": 0.48266666666666663
    },
    {
      "start": 1401.854,
      "end": 1412.572,
      "text": "규정에 따라서는 학장이 교합운영위원회를 지명하면 그걸로 끝납니다.",
      "speaker": null,
      "confidence": 0.5945714285714285
    },
    {
      "start": 1412.592,
      "end": 1421.247,
      "text": "그런데 우리가 반행적으로 전집행부, 현집행부, 행정실장이 운영이 됐었는데 저희가 좀 안타까운 부분 중에 하나도",
      "speaker": null,
      "confidence": 0.5085
    },
    {
      "start": 1421.227,
      "end": 1425.853,
      "text": "교학운영위원회가 유명무실화 됐었어요.",
      "speaker": null,
      "confidence": 0.6233333333333334
    },
    {
      "start": 1425.873,
      "end": 1430.319,
      "text": "그래서 저희는 활성화를 하려고 합니다.",
      "speaker": null,
      "confidence": 0.6878
    },
    {
      "start": 1430.339,
      "end": 1445.58,
      "text": "대학에 있는 주요 현안이라든가 그런 부분이 한쪽에 정보에 치우쳐 있어서도 안되고 정보 공유할 수도 있고 충분히 의견 교류가 될 수 있는 걸 만들기 위해서 이 부분을 저희가 고민을 해서 한 거니까",
      "speaker": null,
      "confidence": 0.6627741935483871
    },
    {
      "start": 1445.56,
      "end": 1458.852,
      "text": "저희가 좀 잘 운영될 수 있도록 교수님들께서 이걸 승인해 주시면 저희가 그렇게 진행을 하도록 하겠습니다.",
      "speaker": null,
      "confidence": 0.6140000000000001
    },
    {
      "start": 1459.773,
      "end": 1459.873,
      "text": "맞습니다.",
      "speaker": null,
      "confidence": 0.4
    },
    {
      "start": 1460.394,
      "end": 1462.316,
      "text": "최소 3개월 많을 때는 6개월.",
      "speaker": null,
      "confidence": 0.882
    },
    {
      "start": 1477.167,
      "end": 1482.036,
      "text": "그러니까 이거는 저희가 현실적인 문제점이 있어요.",
      "speaker": null,
      "confidence": 0.4683333333333333
    },
    {
      "start": 1482.056,
      "end": 1502.331,
      "text": "일단은 두 분이 지금 여기에 참여를 못하신다는... 그러니까 누군가는 지명을 해야 되는데 누구를 지명하기보다는 각 기관의 기관장들이 오시면 병원장님 같은 경우는 임상 쪽에 있는 관련 내용을 하실 수 있을 것 같고 동물의학연구소는 연구비라든가 연구 쪽에 관련된 내용",
      "speaker": null,
      "confidence": 0.5996756756756757
    },
    {
      "start": 1578.49,
      "end": 1592.578,
      "text": "이 부분은 저희들한테 위임을 해주시면 물론 이 틀은 변화가 있을지도 없을지도 모르겠습니다만 의견을 개진해보고 참여하시는 분들은 같이 가고",
      "speaker": null,
      "confidence": 0.6012222222222223
    },
    {
      "start": 1592.558,
      "end": 1603.431,
      "text": "그 다음에 못하시겠다는 분들은 저희가 학장으로서 부탁을 드려서 이 학사운영회원회를 교학운영회원회 팀을 구성도록 하겠습니다.",
      "speaker": null,
      "confidence": 0.5162857142857142
    },
    {
      "start": 1790.114,
      "end": 1792.21,
      "text": "크림길?",
      "speaker": null,
      "confidence": 0.458
    },
    {
      "start": 2367.192,
      "end": 2374.684,
      "text": "그리고 대토도 얘기를 말씀을 하셨습니다.",
      "speaker": null,
      "confidence": 0.5476000000000001
    },
    {
      "start": 2431.147,
      "end": 2442.916,
      "text": "일단 본부 재무과하고 총장님 의견은 어떠시냐 그러면 저희가 행위를 하다가 어느 시점에서부터 아무것도 안 했어요.",
      "speaker": null,
      "confidence": 0.6471999999999999
    },
    {
      "start": 2443.497,
      "end": 2450.144,
      "text": "유휘부지가 있다거나 그런 부분은 어떻게 사용할 것인가 사용계획을 저희가 제출합니다.",
      "speaker": null,
      "confidence": 0.635
    },
    {
      "start": 2450.204,
      "end": 2468.765,
      "text": "사용계획을 제출하면 본부에서는 그 내용을 보고 타당성이 있다 없다를 판단해서 반납을 할 것인지 유지를 할 것인지 결정을 하고 있는데 지금 재무부하고 재무과는 통장님한테 보고하기를 위원회가 있었겠죠.",
      "speaker": null,
      "confidence": 0.8282692307692306
    },
    {
      "start": 2468.785,
      "end": 2472.289,
      "text": "그래서 수익과대학은 이 토지에 대해서",
      "speaker": null,
      "confidence": 0.6362
    },
    {
      "start": 2472.438,
      "end": 2474.415,
      "text": "사용할 계획이",
      "speaker": null,
      "confidence": 0.78
    },
    {
      "start": 2474.547,
      "end": 2502.647,
      "text": "의지가 없다 판단이 그렇게 돼서 일단 보고는 들어갔습니다 작년 12월에 작년 12월에 들어갔고 지금 이제 이게 빨라지게 되면 2월 말이 되면 기재부로 반납이 되게 되고 지금 절차가 그렇게 돼 있는데 제가 우리 교수회의 논의할 때까지 그걸 제가 스탑을 좀 부탁을 드렸어요 지금 총장님한테 보고 간 것도",
      "speaker": null,
      "confidence": 0.7045000000000001
    },
    {
      "start": 2502.627,
      "end": 2516.687,
      "text": "큰 대학들, 부산대학이나 서울대학 이런 데는 캠퍼스 기회로 링도로",
      "speaker": null,
      "confidence": 0.43444444444444447
    },
    {
      "start": 2617.124,
      "end": 2641.849,
      "text": "법의 테두리에서 법으로는 법적으로는 경상남도 김해시에서는 불허를 했습니다 우리가 의견을 냈었던 거 3페이지 맨 마지막에 보면 우리가 하고자 했던 야생동물센터는 거기서 최종적으로 안 된다 경상남도도 안 된다 김해시도 안 된다 그 다음에 이게 24년도에 나왔는데",
      "speaker": null,
      "confidence": 0.7807999999999998
    },
    {
      "start": 2641.829,
      "end": 2666.132,
      "text": "근데 그 이후에 그럼 우리가 뭐를 다 선거를 해야 될 부분을 이제 의견을 만들고 이게 동물 야생동물 센터가 아니면은 뭐 우리가 좀 논의 잠깐 했었던 거 뭐 재활센터가 됐든 아니면 뭐 야생동물 뭐 탐방로가 됐든 뭐가 그런 부분이 됐으면은 본부 측에서도 아 노력을 했구나 시 도하고도 얘기가 됐구나 그런 식으로 돼서 자기네들도 할 부분이 충분히 있는데",
      "speaker": null,
      "confidence": 0.7264285714285714
    },
    {
      "start": 2666.112,
      "end": 2668.675,
      "text": "2년간 그 다음에는 공백이었다는 얘기죠.",
      "speaker": null,
      "confidence": 0.8107999999999999
    },
    {
      "start": 2669.116,
      "end": 2677.787,
      "text": "그 다음에 한 번 정도는 더 유예를 해주는데 작년까지 되는데 이게 이제 문제가 되는 게 뭐냐면 감사에 나오면 항상 지적이 돼요.",
      "speaker": null,
      "confidence": 0.7824285714285715
    },
    {
      "start": 2677.887,
      "end": 2680.21,
      "text": "본부에서는 이게 이제 계륵인 거라.",
      "speaker": null,
      "confidence": 0.6158
    },
    {
      "start": 2680.23,
      "end": 2681.772,
      "text": "니네 쓰지도 않으면서 왜 잡고 있느냐.",
      "speaker": null,
      "confidence": 0.8146666666666667
    },
    {
      "start": 2682.233,
      "end": 2684.556,
      "text": "쓸 수 있는 사람한테 주면 되는데 이게 왜 잡고 있냐.",
      "speaker": null,
      "confidence": 0.8318999999999999
    },
    {
      "start": 2684.696,
      "end": 2686.078,
      "text": "그런 부분이 있어서",
      "speaker": null,
      "confidence": 0.855
    },
    {
      "start": 2686.058,
      "end": 2701.317,
      "text": "오늘 결정할 사항은 그래서 제가 드리고 싶은 말씀이 지금 야생동물센터가 아예 안 됐으니 다른 의견이라도 혹시 있으시면 법의 테두리를 벗어나지 않는 범인에서 지금 현재로 법의 테두리에서 벗어나지 않는 것은",
      "speaker": null,
      "confidence": 0.8213793103448274
    },
    {
      "start": 2701.297,
      "end": 2704.924,
      "text": "현재는 우리가 하고자 하는 건 없습니다.",
      "speaker": null,
      "confidence": 0.535
    },
    {
      "start": 2821.316,
      "end": 2822.397,
      "text": "당장 근데 저희가.",
      "speaker": null,
      "confidence": 0.9303333333333335
    },
    {
      "start": 2890.45,
      "end": 2892.933,
      "text": "국유재산하고 지방재산을 나누게 돼.",
      "speaker": null,
      "confidence": 0.46424999999999994
    },
    {
      "start": 2909.112,
      "end": 2917.002,
      "text": "지금 그래서 현재로서는 저희가 동물사육시설 그런 것도 전혀 안 되고 규정대로입니다.",
      "speaker": null,
      "confidence": 0.7288181818181818
    },
    {
      "start": 2917.022,
      "end": 2920.006,
      "text": "교육시설도 안 됩니다.",
      "speaker": null,
      "confidence": 0.871
    },
    {
      "start": 2920.026,
      "end": 2934.404,
      "text": "물론 노력을 해가지고 예전에 환경청하고 지자체하고 교육부하고 학교하고 이렇게 돼서 잘 됐으면 좋았을 텐데 그게 안 됐어요.",
      "speaker": null,
      "confidence": 0.8012941176470587
    },
    {
      "start": 2936.72,
      "end": 2937.2,
      "text": "연수원?",
      "speaker": null,
      "confidence": 0.694
    },
    {
      "start": 2937.921,
      "end": 2939.423,
      "text": "연수원으로 어떻게 할까요?",
      "speaker": null,
      "confidence": 0.6906666666666667
    },
    {
      "start": 2943.206,
      "end": 2950.953,
      "text": "네, 산업 동물은 아예 안 됩니다.",
      "speaker": null,
      "confidence": 0.754
    },
    {
      "start": 2964.04,
      "end": 2990.79,
      "text": "이름만 그렇게 붙이고 실습은 할 때만 동물을 가져오는 식으로 해서 숙박시설 넣고 애들 체험하고 일반인 체험하고 이런 식으로 남부권 산업동물 연구소 그러면 지금 말씀하신 대로 있잖아요 이게 어떻게 될지 모릅니다 근데 계획서 상에서 저희가 좀 논의를 해 본 다음에 지금 현재 우리가 제출한 게 없어요",
      "speaker": null,
      "confidence": 0.43133333333333335
    },
    {
      "start": 2990.77,
      "end": 3006.563,
      "text": "없다 보니까 그래서 기재부를 반납하겠다고 본부는 결정을 했고 총장님 보고도 끝난 상황인데 남부산업동물 연수원으로 활용하겠다고 의견을 한번 내보는 건 어떨까요?",
      "speaker": null,
      "confidence": 0.8543499999999999
    },
    {
      "start": 3006.583,
      "end": 3009.729,
      "text": "그러면 그 다음에 법률적인 걸 저희가 논의를 한번 해보도록 하겠습니다.",
      "speaker": null,
      "confidence": 0.6356
    },
    {
      "start": 3009.749,
      "end": 3012.154,
      "text": "근데 받아들여질지 안 받아들일지 몰라요.",
      "speaker": null,
      "confidence": 0.7358
    },
    {
      "start": 3033.65,
      "end": 3034.932,
      "text": "자 다음으로 넘어가실까요?",
      "speaker": null,
      "confidence": 0.5336666666666666
    },
    {
      "start": 3202.495,
      "end": 3203.517,
      "text": "거제도로 가십시오.",
      "speaker": null,
      "confidence": 0.646
    },
    {
      "start": 3204.138,
      "end": 3205.38,
      "text": "워크샵 해야 됩니다.",
      "speaker": null,
      "confidence": 0.6789999999999999
    },
    {
      "start": 3374.272,
      "end": 3376.614,
      "text": "저희 수의과 대학 업무보고가 있습니다.",
      "speaker": null,
      "confidence": 0.4513999999999999
    },
    {
      "start": 3431.441,
      "end": 3433.404,
      "text": "감사합니다.",
      "speaker": null,
      "confidence": 0.573
    },
    {
      "start": 3474.962,
      "end": 3476.384,
      "text": "차를 주차로 바꿨다.",
      "speaker": null,
      "confidence": 0.45966666666666667
    },
    {
      "start": 3507.247,
      "end": 3513.634,
      "text": "여기 바로 위에 자판기 있고 애들 앉아서 도시락 물어요.",
      "speaker": null,
      "confidence": 0.6292222222222222
    },
    {
      "start": 3658.244,
      "end": 3661.508,
      "text": "차량 소변은 신부학장님이 다 하신 거죠?",
      "speaker": null,
      "confidence": 0.538
    },
    {
      "start": 3661.528,
      "end": 3661.568,
      "text": "네.",
      "speaker": null,
      "confidence": 0.932
    },
    {
      "start": 3662.068,
      "end": 3679.508,
      "text": "차량 걱정 안 하셔도 됩니다.",
      "speaker": null,
      "confidence": 0.5740000000000001
    }
  ]
}